anypytools/__init__.py
anypytools/abcutils.py
anypytools/datautils.py
anypytools/h5py_wrapper.py
anypytools/jobpopen.py
anypytools/macro_commands.py
anypytools/macroutils.py
anypytools/pytest_plugin.py
anypytools/tools.py
anypytools-1.20.4.dist-info/entry_points.txt
anypytools-1.20.4.dist-info/licenses/LICENSE.txt
anypytools-1.20.4.dist-info/WHEEL
anypytools-1.20.4.dist-info/METADATA
anypytools-1.20.4.dist-info/RECORD
