Metadata-Version: 2.4
Name: anypytools
Version: 1.20.4
Summary: Python tools and utilities for working with the AnyBody Modeling System
Keywords: AnyBody Modeling System,AnyScript
Author-email: Morten Enemark Lund <melund@gmail.com>
Requires-Python: >=3.10
License-Expression: MIT
Classifier: Development Status :: 5 - Production/Stable
Classifier: Programming Language :: Python :: 3.10
Classifier: Programming Language :: Python :: 3.11
Classifier: Programming Language :: Python :: 3.12
Classifier: Framework :: Pytest
Classifier: Intended Audience :: Science/Research
Classifier: Operating System :: OS Independent
Classifier: Topic :: Scientific/Engineering
License-File: LICENSE.txt
Requires-Dist: numpy
Requires-Dist: scipy
Requires-Dist: rich
Requires-Dist: pywin32; platform_system == 'Windows'
Requires-Dist: h5py ; extra == "full"
Requires-Dist: jupyter ; extra == "full"
Requires-Dist: matplotlib ; extra == "full"
Requires-Dist: pydoe ; extra == "full"
Requires-Dist: pandas ; extra == "full"
Requires-Dist: ipywidgets ; extra == "full"
Requires-Dist: pytest ; extra == "full"
Project-URL: Code, https://github.com/AnyBody-Research-Group/AnyPyTools
Project-URL: Documentation, https://anybody-research-group.github.io/anypytools-docs/
Project-URL: Homepage, https://anybody-research-group.github.io/anypytools-docs/
Provides-Extra: full
